chasgimqtt/__init__.py
chasgimqtt/cli.py
chasgimqtt/server.py
chasgimqtt-0.3.0.dist-info/LICENSE
chasgimqtt-0.3.0.dist-info/METADATA
chasgimqtt-0.3.0.dist-info/WHEEL
chasgimqtt-0.3.0.dist-info/entry_points.txt
chasgimqtt-0.3.0.dist-info/top_level.txt
chasgimqtt-0.3.0.dist-info/RECORD
