Metadata-Version: 2.1
Name: chasgimqtt
Version: 0.3.0
Summary: Interface between MQTT broker and ASGI and Channels 2.0 compatible
Home-page: https://github.com/xavierlesa/channels-asgi-mqtt
Author: Xavier Lesa
Author-email: xavierlesa@gmail.com
License: GPLv3+
Platform: UNKNOWN
Classifier: Development Status :: 4 - Beta
Classifier: Environment :: Web Environment
Classifier: License :: OSI Approved :: GNU General Public License v3 or later (GPLv3+)
Classifier: Framework :: Django
Classifier: Operating System :: OS Independent
Classifier: Programming Language :: Python
Classifier: Programming Language :: Python :: 3
Classifier: Programming Language :: Python :: 3.4
Classifier: Programming Language :: Python :: 3.5
Classifier: Programming Language :: Python :: 3.6
Classifier: Topic :: Internet :: WWW/HTTP
Requires-Dist: paho-mqtt
